setup.py
pageone/__init__.py
pageone/core.py
pageone/exc.py
pageone.egg-info/PKG-INFO
pageone.egg-info/SOURCES.txt
pageone.egg-info/dependency_links.txt
pageone.egg-info/namespace_packages.txt
pageone.egg-info/not-zip-safe
pageone.egg-info/requires.txt
pageone.egg-info/top_level.txt