Metadata-Version: 1.1
Name: pageone
Version: 0.2.2
Summary: a module for polling urls and stats from homepages
Home-page: http://github.com/newslnyx/pageone
Author: Brian Abelson
Author-email: brian@newslynx.org
License: MIT
Platform: UNKNOWN
Classifier: Development Status :: 3 - Alpha
Classifier: Intended Audience :: Developers
Classifier: License :: OSI Approved :: MIT License
Classifier: Operating System :: OS Independent
Classifier: Programming Language :: Python
